client/__init__.py
client/client.py
client/setup.py
client/client/__init__.py
client/client/add_contact.py
client/client/database.py
client/client/del_contact.py
client/client/main_window.py
client/client/main_window_conv.py
client/client/set_client_dialog.py
client/client/transport.py
client/common/__init__.py
client/common/config_startup.py
client/common/decos.py
client/common/descriptors.py
client/common/errors.py
client/common/metaclasses.py
client/common/utils.py
client/common/variables.py
client/logs/__init__.py
client/unit_tests/__init__.py
client/unit_tests/test_client.py
client/unit_tests/test_server.py
client/unit_tests/test_utils.py
client/unit_tests/test_valid.py
client_mess_proj-0.0.2.dist-info/METADATA
client_mess_proj-0.0.2.dist-info/WHEEL
client_mess_proj-0.0.2.dist-info/top_level.txt
client_mess_proj-0.0.2.dist-info/RECORD
